moneysnake/__init__.py
moneysnake/__init__.pyi
moneysnake/client.py
moneysnake/client.pyi
moneysnake/contact.py
moneysnake/contact.pyi
moneysnake/custom_field_model.py
moneysnake/custom_field_model.pyi
moneysnake/external_sales_invoice.py
moneysnake/external_sales_invoice.pyi
moneysnake/financial_mutation.py
moneysnake/financial_mutation.pyi
moneysnake/financial_statement.py
moneysnake/financial_statement.pyi
moneysnake/model.py
moneysnake/model.pyi
moneysnake/payment.py
moneysnake/payment.pyi
moneysnake/tax_rate.py
moneysnake/tax_rate.pyi
moneysnake-0.2.3.dist-info/METADATA
moneysnake-0.2.3.dist-info/WHEEL
moneysnake-0.2.3.dist-info/licenses/LICENSE
moneysnake-0.2.3.dist-info/RECORD
