Metadata-Version: 2.4
Name: moneysnake
Version: 0.2.3
Summary: Moneybird SDK for Python
License: MIT
License-File: LICENSE
Author: ArjanCodes
Requires-Python: >=3.12,<4.0
Classifier: License :: OSI Approved :: MIT License
Classifier: Programming Language :: Python :: 3
Classifier: Programming Language :: Python :: 3.12
Classifier: Programming Language :: Python :: 3.13
Classifier: Programming Language :: Python :: 3.14
Requires-Dist: freezegun (>=1.5.5,<2.0.0)
Requires-Dist: httpx (>=0.27.2,<0.28.0)
Requires-Dist: pydantic (>=2.10.6,<3.0.0)
